nolimit.py
nolimit_scanner-1.2.dist-info/LICENSE
nolimit_scanner-1.2.dist-info/METADATA
nolimit_scanner-1.2.dist-info/WHEEL
nolimit_scanner-1.2.dist-info/top_level.txt
nolimit_scanner-1.2.dist-info/RECORD
